reforge/__init__.py
reforge/application.py
reforge/color.py
reforge/components.py
reforge/context.py
reforge/entity.py
reforge/font.py
reforge/input.py
reforge/logger.py
reforge/math.py
reforge/renderer.py
reforge/scene.py
reforge/surface.py
reforge/utils.py
reforge/window.py
reforge/api/__init__.py
reforge/api/event.py
reforge/api/instanceHandler.py
reforge/api/logger.py
reforge/api/pygame/__init__.py
reforge/api/pygame/context.py
reforge/api/pygame/eventHandler.py
reforge/api/pygame/font.py
reforge/api/pygame/input.py
reforge/api/pygame/renderer.py
reforge/api/pygame/surface.py
reforge/api/pygame/window.py
reforge/api/sdl2/__init__.py
reforge/api/sdl2/context.py
reforge/api/sdl2/eventHandler.py
reforge/api/sdl2/font.py
reforge/api/sdl2/input.py
reforge/api/sdl2/renderer.py
reforge/api/sdl2/surface.py
reforge/api/sdl2/window.py
reforge/api/sdl3/__init__.py
reforge/api/sdl3/context.py
reforge/api/sdl3/eventHandler.py
reforge/api/sdl3/font.py
reforge/api/sdl3/input.py
reforge/api/sdl3/renderer.py
reforge/api/sdl3/surface.py
reforge/api/sdl3/window.py
reforge-0.1.1.dist-info/licenses/LICENSE
reforge-0.1.1.dist-info/METADATA
reforge-0.1.1.dist-info/WHEEL
reforge-0.1.1.dist-info/top_level.txt
reforge-0.1.1.dist-info/RECORD
