Metadata-Version: 2.4
Name: ReForge
Version: 0.1.1
Summary: A 2D game engine written in Python using both PyGame, PySDL2 and PySDL3.
Author-email: Yusuf Rençber <aermoss.0@gmail.com>
Project-URL: Repository, https://github.com/Aermoss/ReForge
Project-URL: Issues, https://github.com/Aermoss/ReForge/issues
Classifier: Development Status :: 3 - Alpha
Classifier: Intended Audience :: Developers
Classifier: Operating System :: POSIX :: Linux
Classifier: Operating System :: MacOS :: MacOS X
Classifier: Operating System :: Microsoft :: Windows
Classifier: License :: OSI Approved :: MIT License
Classifier: Programming Language :: Python :: 3.10
Classifier: Programming Language :: Python :: 3.11
Classifier: Programming Language :: Python :: 3.12
Classifier: Programming Language :: Python :: 3.13
Classifier: Programming Language :: Python :: 3.14
License-File: LICENSE
Requires-Dist: pygame
Requires-Dist: pysdl2
Requires-Dist: pysdl2-dll
Requires-Dist: pysdl3
Dynamic: license-file
